{
  "index_name": "adonisjs_next",
  "start_urls": [
    {
      "url": "https://docs.adonisjs.com/reference/",
      "page_rank": "4",
      "variables": {
        "zone": "reference"
      }
    },
    {
      "url": "https://docs.adonisjs.com/guides/",
      "page_rank": "3",
      "variables": {
        "zone": "guides"
      }
    },
    {
      "url": "https://docs.adonisjs.com/cookbooks/",
      "page_rank": "2",
      "variables": {
        "zone": "cookbooks"
      }
    },
    {
      "url": "https://docs.adonisjs.com/releases/",
      "page_rank": "1",
      "variables": {
        "zone": "releases"
      }
    }
  ],
  "stop_urls": [],
  "selectors": {
    "default": {
      "lvl0": {
        "selector": "//*nav//*[contains(@class,'active')]/preceding::h3[1]",
        "default_value": "Documentation",
        "type": "xpath",
        "global": true
      },
      "lvl1": ".markdown h1",
      "lvl2": ".markdown h2",
      "lvl3": ".markdown h3",
      "lvl4": ".markdown h4",
      "text": ".markdown p, .markdown li"
    }
  },
  "conversation_id": [
    "1156190793"
  ],
  "nb_hits": 69556
}
