{
  "index_name": "atlassianps",
  "sitemap_urls": [
    "https://atlassianps.org/sitemap.xml"
  ],
  "sitemap_urls_regexs": [
    "/docs/"
  ],
  "stop_urls": [],
  "selectors": {
    "lvl0": ".page.documentation *[data-algolia=\"lvl0\"]",
    "lvl1": ".page.documentation *[data-algolia=\"lvl1\"]",
    "lvl2": ".page.documentation section.content h1:first-of-type",
    "lvl3": ".page.documentation section.content h2",
    "lvl4": ".page.documentation section.content h3",
    "lvl5": ".page.documentation section.content h4",
    "text": ".page.documentation section.content p, .page.documentation section.content li, .page.documentation section.content pre"
  },
  "strip_chars": "\u2014\u2013 --_",
  "min_indexed_level": 2,
  "conversation_id": [
    "434891628"
  ],
  "nb_hits": 5349
}