{
  "index_name": "bolt",
  "start_urls": [
    {
      "url": "https://docs.bolt.cm/(?P<version>.*?)/getting-started/introduction",
      "variables": {
        "version": [
          "4.0",
          "3.7",
          "3.6",
          "3.5",
          "3.4",
          "3.3",
          "3.2",
          "3.1",
          "3.0",
          "2.2"
        ]
      }
    },
    {
      "url": "https://docs.bolt.cm/(?P<version>.*?)/.*",
      "variables": {
        "version": [
          "4.0",
          "3.7",
          "3.6",
          "3.5",
          "3.4",
          "3.3",
          "3.2",
          "3.1",
          "3.0",
          "2.2"
        ]
      }
    }
  ],
  "selectors": {
    "lvl0": ".content h1",
    "lvl1": ".content h2",
    "lvl2": ".content h3",
    "lvl3": ".content h4",
    "text": ".content p, .content li, .content code"
  },
  "selectors_exclude": [
    ".quick-links",
    ".community-notice"
  ],
  "stop_content": [
    "404 - Page not found"
  ],
  "js_render": true,
  "conversation_id": [
    "183246755"
  ],
  "nb_hits": 81985
}