{
  "index_name": "cloudflare-access",
  "start_urls": ["https://developers.cloudflare.com/access/"],
  "sitemap_urls": ["https://developers.cloudflare.com/access/sitemap.xml"],
  "stop_urls": [],
  "selectors": {
    "lvl0": {
      "selector": ".DocsSidebar--nav-item[is-active-root] > a.DocsSidebar--nav-link",
      "default_value": "Documentation"
    },
    "lvl1": ".DocsContent h1",
    "lvl2": ".DocsContent h2",
    "lvl3": ".DocsContent h3",
    "lvl4": ".DocsContent h4",
    "lvl5": ".DocsContent h5",
    "text": ".DocsContent p, .DocsContent li"
  },
  "conversation_id": ["1321224029"],
  "nb_hits": 5396
}
