{
  "index_name": "factoriadigital",
  "start_urls": [
    "https://www.factoriadigital.com/soporte/es/tutoriales-y-preguntas-frecuentes"
  ],
  "stop_urls": [],
  "selectors": {
    "lvl0": {
      "selector": "//*[@id='desk_content']/*[contains(@class, 'breadcrumb')]/a[2]",
      "type": "xpath",
      "global": true
    },
    "lvl1": "#desk_content h1",
    "lvl2": "#desk_content h2",
    "lvl3": "#desk_content h3",
    "lvl4": "#desk_content h4",
    "lvl5": "#desk_content h5",
    "text": "#desk_content p, #desk_content li"
  },
  "min_indexed_level": 1,
  "conversation_id": [
    "571416017"
  ],
  "nb_hits": 9168
}