{
  "index_name": "home-assistant",
  "start_urls": [
    "https://www.home-assistant.io/docs/",
    "https://www.home-assistant.io/hassio/",
    "https://www.home-assistant.io/lovelace/",
    "https://www.home-assistant.io/getting-started/",
    "https://www.home-assistant.io/developers/"
  ],
  "sitemap_urls": [
    "https://www.home-assistant.io/sitemap.xml"
  ],
  "stop_urls": [],
  "selectors": {
    "lvl0": {
      "selector": "h1.title.delta",
      "global": true,
      "default_value": "Documentation"
    },
    "lvl1": {
      "selector": "(//ul[contains(@class,'sidebar-menu')]/li[.//a[contains(@class,'active')]]/b | //ul[contains(@class,'sidebar-menu')]/li[.//a[contains(@class,'active')]]/a)[1]",
      "type": "xpath",
      "global": true,
      "default_value": "Chapter"
    },
    "lvl2": "article h1",
    "lvl3": "article h2",
    "lvl4": "article h3",
    "text": "article p, article li"
  },
  "only_content_level": true,
  "conversation_id": [
    "382758605"
  ],
  "nb_hits": 4295
}