{
  "index_name": "parseplatform",
  "start_urls": [
    {
      "url": "https://docs.parseplatform.org/parse-server/guide/",
      "tags": [
        "parse-server"
      ]
    },
    {
      "url": "https://docs.parseplatform.org/ios/guide/",
      "tags": [
        "ios"
      ]
    },
    {
      "url": "https://docs.parseplatform.org/android/guide/",
      "tags": [
        "android"
      ]
    },
    {
      "url": "https://docs.parseplatform.org/js/guide/",
      "tags": [
        "js"
      ]
    },
    {
      "url": "https://docs.parseplatform.org/dotnet/guide/",
      "tags": [
        "dotnet"
      ]
    },
    {
      "url": "https://docs.parseplatform.org/macos/guide/",
      "tags": [
        "macos"
      ]
    },
    {
      "url": "https://docs.parseplatform.org/unity/guide/",
      "tags": [
        "unity"
      ]
    },
    {
      "url": "https://docs.parseplatform.org/php/guide/",
      "tags": [
        "php"
      ]
    },
    {
      "url": "https://docs.parseplatform.org/arduino/guide/",
      "tags": [
        "arduino"
      ]
    },
    {
      "url": "https://docs.parseplatform.org/embedded_c/guide/",
      "tags": [
        "embedded_c"
      ]
    },
    {
      "url": "https://docs.parseplatform.org/cloudcode/guide/",
      "tags": [
        "cloudcode"
      ]
    },
    {
      "url": "https://docs.parseplatform.org/rest/guide/",
      "tags": [
        "rest"
      ]
    }
  ],
  "stop_urls": [],
  "selectors": {
    "lvl0": {
      "selector": "p.h1 > span",
      "global": true,
      "default_value": "Documentation"
    },
    "lvl1": ".wysiwyg-content h1",
    "lvl2": ".wysiwyg-content h2",
    "lvl3": ".wysiwyg-content h3",
    "lvl4": ".wysiwyg-content h4",
    "lvl5": ".wysiwyg-content h5",
    "text": ".wysiwyg-content p, .wysiwyg-content li"
  },
  "conversation_id": [
    "653702733"
  ],
  "nb_hits": 8154
}