{
  "index_name": "pixelastic_on-circle",
  "start_urls": [
    "https://projects.pixelastic.com/on-circle/"
  ],
  "sitemap_urls": [
    "https://projects.pixelastic.com/on-circle/sitemap.xml"
  ],
  "stop_urls": [],
  "selectors": {
    "lvl0": {
      "selector": "//*[contains(@class,'ds-sidebar')]//*[contains(@class,'DocSearch-active')]/preceding::h3[1]",
      "type": "xpath",
      "global": true,
      "default_value": "Documentation"
    },
    "lvl1": ".DocSearch-content h1",
    "lvl2": ".DocSearch-content h2",
    "lvl3": ".DocSearch-content h3",
    "lvl4": ".DocSearch-content h4",
    "lvl5": ".DocSearch-content h5",
    "lvl6": ".DocSearch-content h6",
    "text": ".DocSearch-content p, .DocSearch-content li"
  },
  "conversation_id": [
    "1278918719"
  ],
  "nb_hits": 40
}