{
  "index_name": "spatie_be",
  "start_urls": [
    {
      "url": "https://spatie.be/docs/(?P<project>.*?)/(?P<version>.*?)/",
      "variables": {
        "version": [
          "v1",
          "v2",
          "v3",
          "v4",
          "v5",
          "v6",
          "v7",
          "v8"
        ],
        "project": [
          "laravel-backup",
          "laravel-medialibrary",
          "laravel-blade-x",
          "laravel-tags",
          "laravel-activitylog",
          "laravel-html",
          "laravel-server-monitor",
          "laravel-uptime-monitor",
          "laravel-slack-slash-command",
          "menu",
          "image",
          "enum",
          "laravel-model-states",
          "laravel-permission",
          "laravel-query-builder",
          "laravel-event-sourcing",
          "laravel-resource-links",
          "laravel-backup-server",
          "laravel-dashboard",
          "laravel-multitenancy",
        ]
      }
    }
  ],
  "stop_urls": [
    "/edit$"
  ],
  "selectors": {
    "lvl0": "wrap h1",
    "lvl1": "wrap h2",
    "lvl2": "wrap h3",
    "lvl3": "wrap h4",
    "lvl4": "wrap h5",
    "text": "wrap p"
  },
  "selectors_exclude": [
    "footer",
    "header"
  ],
  "conversation_id": [
    "229197199"
  ],
  "nb_hits": 6176
}
