{
  "index_name": "vue_element_admin",
  "start_urls": [
    "https://panjiachen.github.io/vue-element-admin-site/"
  ],
  "stop_urls": [
    "\\?",
    "/donate"
  ],
  "selectors": {
    "lvl0": ".content h1",
    "lvl1": ".content h2",
    "lvl2": ".content h3",
    "lvl3": ".content h4",
    "lvl4": ".content h5",
    "text": ".content p, .content li",
    "lang": {
      "selector": "/html/@lang",
      "type": "xpath",
      "global": true,
      "default_value": "en-US"
    }
  },
  "custom_settings": {
    "attributesForFaceting": [
      "lang"
    ]
  },
  "strip_chars": " .,;:#",
  "conversation_id": [
    "589544845"
  ],
  "nb_hits": 2199
}